missingdrawables.py
android_missingdrawables-1.0.data/scripts/missingdrawables
android_missingdrawables-1.0.dist-info/DESCRIPTION.rst
android_missingdrawables-1.0.dist-info/pydist.json
android_missingdrawables-1.0.dist-info/WHEEL
android_missingdrawables-1.0.dist-info/entry_points.txt
android_missingdrawables-1.0.dist-info/top_level.txt
android_missingdrawables-1.0.dist-info/METADATA
android_missingdrawables-1.0.dist-info/RECORD
