Metadata-Version: 2.0
Name: android-missingdrawables
Version: 1.0
Summary: Easily find out for which density buckets your drawables are missing.
Home-page: https://github.com/hannesstruss/android-missingdrawables
Author: Hannes Struss
Author-email: x@hannesstruss.de
License: MIT
Platform: UNKNOWN
Classifier: Development Status :: 5 - Production/Stable
Classifier: Intended Audience :: Developers
Classifier: Natural Language :: English
Classifier: License :: OSI Approved :: MIT License
Classifier: Operating System :: OS Independent
Classifier: Programming Language :: Python
Classifier: Programming Language :: Python :: 2.6
Classifier: Programming Language :: Python :: 2.7
